cmdline_preparse_hook/__init__.py
cmdline_preparse_hook/__main__.py
cmdline_preparse_hook/plugin.py
cmdline_preparation_hook-3.1.4.dist-info/METADATA
cmdline_preparation_hook-3.1.4.dist-info/WHEEL
cmdline_preparation_hook-3.1.4.dist-info/entry_points.txt
cmdline_preparation_hook-3.1.4.dist-info/top_level.txt
cmdline_preparation_hook-3.1.4.dist-info/RECORD
