Metadata-Version: 2.2
Name: cmdline-preparation-hook
Version: 3.1.4
Summary: Pytest hook for custom argument handling and Allure reporting. This plugin allows you to add arguments before running a test.
Author-email: Yevhen Halitsyn <halitsyny@science.regn.net>
License: MIT
